tpu_mlir_test/__init__.py
tpu_mlir_test/entry.py
tpu_mlir_test/entryconfig.py
tpu_mlir_test-2.49.data/scripts/envsetup.sh
tpu_mlir_test-2.49.dist-info/LICENSE
tpu_mlir_test-2.49.dist-info/METADATA
tpu_mlir_test-2.49.dist-info/WHEEL
tpu_mlir_test-2.49.dist-info/entry_points.txt
tpu_mlir_test-2.49.dist-info/top_level.txt
tpu_mlir_test-2.49.dist-info/RECORD
